[
  {
    "OfficialId": "22840",
    "VisOrHome": "Home",
    "JerseyNum": "0",
    "FirstName": "Josh",
    "LastName": "Gordon",
    "LastNameSuffix": "",
    "Position": "WR",
    "PositionLongName": "",
    "NAbbrev": "J. Gordon",
    "Height": "6'3\"",
    "Weight": "224",
    "DOB": "4/13/1991",
    "POB": "",
    "Age": 31,
    "Hometown": "",
    "Country": "",
    "CountryCode": "",
    "Nickname": "",
    "InjuryStatus": "",
    "InjuryDesc": "",
    "Headshot": "",
    "IsStarting": true,
    "Initials": "",
    "TrackingId": "",
    "TeamId": "6",
    "Affiliate": "",
    "CloudHeadshotURL": "",
    "SquadId": "",
    "College": "",
    "LeagueStatus": "",
    "Participated": true,
    "PreviousTeamId": ""
  },
  {
    "OfficialId": "22377",
    "VisOrHome": "Home",
    "JerseyNum": "1",
    "FirstName": "Bryce",
    "LastName": "Thompson",
    "LastNameSuffix": "",
    "Position": "DB",
    "PositionLongName": "",
    "NAbbrev": "B. Thompson",
    "Height": "5'10\"",
    "Weight": "182",
    "DOB": "9/20/1999",
    "POB": "",
    "Age": 23,
    "Hometown": "",
    "Country": "",
    "CountryCode": "",
    "Nickname": "",
    "InjuryStatus": "",
    "InjuryDesc": "",
    "GfxId": 1,
    "Headshot": "",
    "IsStarting": true,
    "Initials": "",
    "TrackingId": "",
    "TeamId": "6",
    "Affiliate": "",
    "CloudHeadshotURL": "",
    "SquadId": "",
    "College": "",
    "LeagueStatus": "",
    "Participated": true,
    "PreviousTeamId": ""
  },
  {
    "OfficialId": "21919",
    "VisOrHome": "Home",
    "JerseyNum": "2",
    "FirstName": "Antoine",
    "LastName": "Brooks",
    "LastNameSuffix": "",
    "Position": "DB",
    "PositionLongName": "",
    "NAbbrev": "A. Brooks",
    "Height": "5'10\"",
    "Weight": "220",
    "DOB": "10/28/1997",
    "POB": "",
    "Age": 25,
    "Hometown": "",
    "Country": "",
    "CountryCode": "",
    "Nickname": "",
    "InjuryStatus": "",
    "InjuryDesc": "",
    "GfxId": 2,
    "Headshot": "",
    "IsStarting": true,
    "Initials": "",
    "TrackingId": "",
    "TeamId": "6",
    "Affiliate": "",
    "CloudHeadshotURL": "",
    "SquadId": "",
    "College": "",
    "LeagueStatus": "",
    "Participated": true,
    "PreviousTeamId": ""
  },
  {
    "OfficialId": "21203",
    "VisOrHome": "Home",
    "JerseyNum": "3",
    "FirstName": "Jahcour",
    "LastName": "Pearson",
    "LastNameSuffix": "",
    "Position": "WR",
    "PositionLongName": "",
    "NAbbrev": "J. Pearson",
    "Height": "5'7\"",
    "Weight": "178",
    "DOB": "",
    "POB": "",
    "Hometown": "",
    "Country": "",
    "CountryCode": "",
    "Nickname": "",
    "InjuryStatus": "",
    "InjuryDesc": "",
    "GfxId": 3,
    "Headshot": "",
    "IsStarting": true,
    "Initials": "",
    "TrackingId": "",
    "TeamId": "6",
    "Affiliate": "",
    "CloudHeadshotURL": "https://res.cloudinary.com/xfl-production/image/upload/v1668132138/xfl-prod/headshots/Jahcour_Pearson_21203.png",
    "SquadId": "",
    "College": "",
    "LeagueStatus": "",
    "Participated": true,
    "PreviousTeamId": ""
  },
  {
    "OfficialId": "22035",
    "VisOrHome": "Home",
    "JerseyNum": "4",
    "FirstName": "Juwan",
    "LastName": "Green",
    "LastNameSuffix": "",
    "Position": "WR",
    "PositionLongName": "",
    "NAbbrev": "J. Green",
    "Height": "6'0\"",
    "Weight": "181",
    "DOB": "7/1/1998",
    "POB": "",
    "Age": 24,
    "Hometown": "",
    "Country": "",
    "CountryCode": "",
    "Nickname": "",
    "InjuryStatus": "",
    "InjuryDesc": "",
    "GfxId": 4,
    "Headshot": "",
    "Initials": "",
    "TrackingId": "",
    "TeamId": "6",
    "Affiliate": "",
    "CloudHeadshotURL": "",
    "SquadId": "",
    "College": "",
    "LeagueStatus": "",
    "Participated": true,
    "PreviousTeamId": ""
  },
  {
    "OfficialId": "20836",
    "VisOrHome": "Home",
    "JerseyNum": "5",
    "FirstName": "Chris",
    "LastName": "Jones",
    "LastNameSuffix": "",
    "Position": "DB",
    "PositionLongName": "",
    "NAbbrev": "C. Jones",
    "Height": "5'11\"",
    "Weight": "200",
    "DOB": "8/13/1995",
    "POB": "",
    "Age": 27,
    "Hometown": "",
    "Country": "",
    "CountryCode": "",
    "Nickname": "",
    "InjuryStatus": "",
    "InjuryDesc": "",
    "GfxId": 5,
    "Headshot": "",
    "IsStarting": true,
    "Initials": "",
    "TrackingId": "",
    "TeamId": "6",
    "Affiliate": "",
    "CloudHeadshotURL": "https://res.cloudinary.com/xfl-production/image/upload/v1668132138/xfl-prod/headshots/Chris_Jones_20836.png",
    "SquadId": "",
    "College": "",
    "LeagueStatus": "",
    "Participated": true,
    "PreviousTeamId": ""
  },
  {
    "OfficialId": "21979",
    "VisOrHome": "Home",
    "JerseyNum": "6",
    "FirstName": "Ben",
    "LastName": "DiNucci",
    "LastNameSuffix": "",
    "Position": "QB",
    "PositionLongName": "",
    "NAbbrev": "B. DiNucci",
    "Height": "6'0\"",
    "Weight": "208",
    "DOB": "11/24/1996",
    "POB": "",
    "Age": 26,
    "Hometown": "",
    "Country": "",
    "CountryCode": "",
    "Nickname": "",
    "InjuryStatus": "",
    "InjuryDesc": "",
    "GfxId": 6,
    "Headshot": "",
    "IsStarting": true,
    "Initials": "",
    "TrackingId": "",
    "TeamId": "6",
    "Affiliate": "",
    "CloudHeadshotURL": "",
    "SquadId": "",
    "College": "",
    "LeagueStatus": "",
    "Participated": true,
    "PreviousTeamId": ""
  },
  {
    "OfficialId": "21620",
    "VisOrHome": "Home",
    "JerseyNum": "8",
    "FirstName": "Tre",
    "LastName": "Walker",
    "LastNameSuffix": "",
    "Position": "LB",
    "PositionLongName": "",
    "NAbbrev": "T. Walker",
    "Height": "6'0\"",
    "Weight": "235",
    "DOB": "",
    "POB": "",
    "Hometown": "",
    "Country": "",
    "CountryCode": "",
    "Nickname": "",
    "InjuryStatus": "",
    "InjuryDesc": "",
    "GfxId": 8,
    "Headshot": "",
    "IsStarting": true,
    "Initials": "",
    "TrackingId": "",
    "TeamId": "6",
    "Affiliate": "",
    "CloudHeadshotURL": "",
    "SquadId": "",
    "College": "",
    "LeagueStatus": "",
    "Participated": true,
    "PreviousTeamId": ""
  },
  {
    "OfficialId": "22344",
    "VisOrHome": "Home",
    "JerseyNum": "9",
    "FirstName": "Clarence",
    "LastName": "Hicks",
    "LastNameSuffix": "",
    "Position": "LB",
    "PositionLongName": "",
    "NAbbrev": "C. Hicks",
    "Height": "6'1\"",
    "Weight": "225",
    "DOB": "",
    "POB": "",
    "Hometown": "",
    "Country": "",
    "CountryCode": "",
    "Nickname": "",
    "InjuryStatus": "",
    "InjuryDesc": "",
    "GfxId": 9,
    "Headshot": "",
    "Initials": "",
    "TrackingId": "",
    "TeamId": "6",
    "Affiliate": "",
    "CloudHeadshotURL": "",
    "SquadId": "",
    "College": "",
    "LeagueStatus": "",
    "Participated": true,
    "PreviousTeamId": ""
  },
  {
    "OfficialId": "21997",
    "VisOrHome": "Home",
    "JerseyNum": "10",
    "FirstName": "Cameron",
    "LastName": "Nizialek",
    "LastNameSuffix": "",
    "Position": "P",
    "PositionLongName": "",
    "NAbbrev": "C. Nizialek",
    "Height": "6'1\"",
    "Weight": "210",
    "DOB": "",
    "POB": "",
    "Hometown": "",
    "Country": "",
    "CountryCode": "",
    "Nickname": "",
    "InjuryStatus": "",
    "InjuryDesc": "",
    "GfxId": 10,
    "Headshot": "",
    "Initials": "",
    "TrackingId": "",
    "TeamId": "6",
    "Affiliate": "",
    "CloudHeadshotURL": "",
    "SquadId": "",
    "College": "",
    "LeagueStatus": "",
    "Participated": true,
    "PreviousTeamId": ""
  },
  {
    "OfficialId": "22874",
    "VisOrHome": "Home",
    "JerseyNum": "11",
    "FirstName": "Dominik",
    "LastName": "Eberle",
    "LastNameSuffix": "",
    "Position": "K",
    "PositionLongName": "",
    "NAbbrev": "D. Eberle",
    "Height": "6'2\"",
    "Weight": "190",
    "DOB": "",
    "POB": "",
    "Hometown": "",
    "Country": "",
    "CountryCode": "",
    "Nickname": "",
    "InjuryStatus": "",
    "InjuryDesc": "",
    "GfxId": 11,
    "Headshot": "",
    "Initials": "",
    "TrackingId": "",
    "TeamId": "6",
    "Affiliate": "",
    "CloudHeadshotURL": "",
    "SquadId": "",
    "College": "",
    "LeagueStatus": "",
    "Participated": true,
    "PreviousTeamId": ""
  },
  {
    "OfficialId": "21091",
    "VisOrHome": "Home",
    "JerseyNum": "12",
    "FirstName": "Steven",
    "LastName": "Montez",
    "LastNameSuffix": "",
    "Position": "QB",
    "PositionLongName": "",
    "NAbbrev": "S. Montez",
    "Height": "6'4\"",
    "Weight": "231",
    "DOB": "1/14/1997",
    "POB": "",
    "Age": 26,
    "Hometown": "",
    "Country": "",
    "CountryCode": "",
    "Nickname": "",
    "InjuryStatus": "",
    "InjuryDesc": "",
    "GfxId": 12,
    "Headshot": "",
    "Initials": "",
    "TrackingId": "",
    "TeamId": "6",
    "Affiliate": "",
    "CloudHeadshotURL": "https://res.cloudinary.com/xfl-production/image/upload/v1668132138/xfl-prod/headshots/Steven_Montez_21091.png",
    "SquadId": "",
    "College": "",
    "LeagueStatus": "",
    "PreviousTeamId": ""
  },
  {
    "OfficialId": "21284",
    "VisOrHome": "Home",
    "JerseyNum": "13",
    "FirstName": "Jaylon",
    "LastName": "Redd",
    "LastNameSuffix": "",
    "Position": "WR",
    "PositionLongName": "",
    "NAbbrev": "J. Redd",
    "Height": "5'8\"",
    "Weight": "170",
    "DOB": "9/25/1998",
    "POB": "",
    "Age": 24,
    "Hometown": "",
    "Country": "",
    "CountryCode": "",
    "Nickname": "",
    "InjuryStatus": "",
    "InjuryDesc": "",
    "GfxId": 13,
    "Headshot": "",
    "Initials": "",
    "TrackingId": "",
    "TeamId": "6",
    "Affiliate": "",
    "CloudHeadshotURL": "https://res.cloudinary.com/xfl-production/image/upload/v1668132138/xfl-prod/headshots/Jaylon_Redd_21284.png",
    "SquadId": "",
    "College": "",
    "LeagueStatus": "",
    "Participated": true,
    "PreviousTeamId": ""
  },
  {
    "OfficialId": "22856",
    "VisOrHome": "Home",
    "JerseyNum": "14",
    "FirstName": "Harrison",
    "LastName": "Frost",
    "LastNameSuffix": "",
    "Position": "QB",
    "PositionLongName": "",
    "NAbbrev": "H. Frost",
    "Height": "6'1\"",
    "Weight": "197",
    "DOB": "",
    "POB": "",
    "Hometown": "",
    "Country": "",
    "CountryCode": "",
    "Nickname": "",
    "InjuryStatus": "",
    "InjuryDesc": "",
    "GfxId": 14,
    "Headshot": "",
    "Initials": "",
    "Scratch": true,
    "TrackingId": "",
    "TeamId": "6",
    "Affiliate": "",
    "CloudHeadshotURL": "",
    "SquadId": "",
    "College": "",
    "LeagueStatus": "",
    "PreviousTeamId": ""
  },
  {
    "OfficialId": "21695",
    "VisOrHome": "Home",
    "JerseyNum": "15",
    "FirstName": "Damion",
    "LastName": "Willis",
    "LastNameSuffix": "",
    "Position": "WR",
    "PositionLongName": "",
    "NAbbrev": "D. Willis",
    "Height": "6'3\"",
    "Weight": "204",
    "DOB": "6/20/1997",
    "POB": "",
    "Age": 25,
    "Hometown": "",
    "Country": "",
    "CountryCode": "",
    "Nickname": "",
    "InjuryStatus": "",
    "InjuryDesc": "",
    "GfxId": 15,
    "Headshot": "",
    "Initials": "",
    "TrackingId": "",
    "TeamId": "6",
    "Affiliate": "",
    "CloudHeadshotURL": "https://res.cloudinary.com/xfl-production/image/upload/v1668132138/xfl-prod/headshots/Damion_Willis_21695.png",
    "SquadId": "",
    "College": "",
    "LeagueStatus": "",
    "Participated": true,
    "PreviousTeamId": ""
  },
  {
    "OfficialId": "21721",
    "VisOrHome": "Home",
    "JerseyNum": "16",
    "FirstName": "Mykael",
    "LastName": "Wright",
    "LastNameSuffix": "",
    "Position": "DB",
    "PositionLongName": "",
    "NAbbrev": "M. Wright",
    "Height": "5'10\"",
    "Weight": "181",
    "DOB": "",
    "POB": "",
    "Hometown": "",
    "Country": "",
    "CountryCode": "",
    "Nickname": "",
    "InjuryStatus": "",
    "InjuryDesc": "",
    "GfxId": 16,
    "Headshot": "",
    "Initials": "",
    "Scratch": true,
    "TrackingId": "",
    "TeamId": "6",
    "Affiliate": "",
    "CloudHeadshotURL": "",
    "SquadId": "",
    "College": "",
    "LeagueStatus": "",
    "PreviousTeamId": ""
  },
  {
    "OfficialId": "20468",
    "VisOrHome": "Home",
    "JerseyNum": "17",
    "FirstName": "Rojesterman",
    "LastName": "Farris",
    "LastNameSuffix": "",
    "Position": "DB",
    "PositionLongName": "",
    "NAbbrev": "R. Farris",
    "Height": "5'11\"",
    "Weight": "179",
    "DOB": "9/11/1997",
    "POB": "",
    "Age": 25,
    "Hometown": "",
    "Country": "",
    "CountryCode": "",
    "Nickname": "",
    "InjuryStatus": "",
    "InjuryDesc": "",
    "GfxId": 17,
    "Headshot": "",
    "IsStarting": true,
    "Initials": "",
    "TrackingId": "",
    "TeamId": "6",
    "Affiliate": "",
    "CloudHeadshotURL": "",
    "SquadId": "",
    "College": "",
    "LeagueStatus": "",
    "Participated": true,
    "PreviousTeamId": ""
  },
  {
    "OfficialId": "20620",
    "VisOrHome": "Home",
    "JerseyNum": "19",
    "FirstName": "T.J.",
    "LastName": "Hammonds",
    "LastNameSuffix": "",
    "Position": "WR",
    "PositionLongName": "",
    "NAbbrev": "T. Hammonds",
    "Height": "5'9\"",
    "Weight": "185",
    "DOB": "4/24/1998",
    "POB": "",
    "Age": 24,
    "Hometown": "",
    "Country": "",
    "CountryCode": "",
    "Nickname": "",
    "InjuryStatus": "",
    "InjuryDesc": "",
    "GfxId": 19,
    "Headshot": "",
    "Initials": "",
    "TrackingId": "",
    "TeamId": "6",
    "Affiliate": "",
    "CloudHeadshotURL": "",
    "SquadId": "",
    "College": "",
    "LeagueStatus": "",
    "Participated": true,
    "PreviousTeamId": ""
  },
  {
    "OfficialId": "21963",
    "VisOrHome": "Home",
    "JerseyNum": "21",
    "FirstName": "Linden",
    "LastName": "Stephens",
    "LastNameSuffix": "",
    "Position": "DB",
    "PositionLongName": "",
    "NAbbrev": "L. Stephens",
    "Height": "5'11\"",
    "Weight": "190",
    "DOB": "3/21/1995",
    "POB": "",
    "Age": 27,
    "Hometown": "",
    "Country": "",
    "CountryCode": "",
    "Nickname": "",
    "InjuryStatus": "",
    "InjuryDesc": "",
    "GfxId": 21,
    "Headshot": "",
    "Initials": "",
    "TrackingId": "",
    "TeamId": "6",
    "Affiliate": "",
    "CloudHeadshotURL": "",
    "SquadId": "",
    "College": "",
    "LeagueStatus": "",
    "Participated": true,
    "PreviousTeamId": ""
  },
  {
    "OfficialId": "20369",
    "VisOrHome": "Home",
    "JerseyNum": "24",
    "FirstName": "Shabari",
    "LastName": "Davis",
    "LastNameSuffix": "",
    "Position": "DB",
    "PositionLongName": "",
    "NAbbrev": "S. Davis",
    "Height": "6'0\"",
    "Weight": "186",
    "DOB": "",
    "POB": "",
    "Hometown": "",
    "Country": "",
    "CountryCode": "",
    "Nickname": "",
    "InjuryStatus": "",
    "InjuryDesc": "",
    "GfxId": 24,
    "Headshot": "",
    "Initials": "",
    "Scratch": true,
    "TrackingId": "",
    "TeamId": "6",
    "Affiliate": "",
    "CloudHeadshotURL": "https://res.cloudinary.com/xfl-production/image/upload/v1668132138/xfl-prod/headshots/Shabari_Davis_20369.png",
    "SquadId": "",
    "College": "",
    "LeagueStatus": "",
    "PreviousTeamId": ""
  },
  {
    "OfficialId": "20450",
    "VisOrHome": "Home",
    "JerseyNum": "25",
    "FirstName": "Morgan",
    "LastName": "Ellison",
    "LastNameSuffix": "",
    "Position": "RB",
    "PositionLongName": "",
    "NAbbrev": "M. Ellison",
    "Height": "6'0\"",
    "Weight": "238",
    "DOB": "",
    "POB": "",
    "Hometown": "",
    "Country": "",
    "CountryCode": "",
    "Nickname": "",
    "InjuryStatus": "",
    "InjuryDesc": "",
    "GfxId": 25,
    "Headshot": "",
    "Initials": "",
    "TrackingId": "",
    "TeamId": "6",
    "Affiliate": "",
    "CloudHeadshotURL": "https://res.cloudinary.com/xfl-production/image/upload/v1668132138/xfl-prod/headshots/Morgan_Ellison_20450.png",
    "SquadId": "",
    "College": "",
    "LeagueStatus": "",
    "Participated": true,
    "PreviousTeamId": ""
  },
  {
    "OfficialId": "20460",
    "VisOrHome": "Home",
    "JerseyNum": "26",
    "FirstName": "Jordan",
    "LastName": "Evans",
    "LastNameSuffix": "",
    "Position": "LB",
    "PositionLongName": "",
    "NAbbrev": "J. Evans",
    "Height": "6'2\"",
    "Weight": "239",
    "DOB": "1/27/1995",
    "POB": "",
    "Age": 28,
    "Hometown": "",
    "Country": "",
    "CountryCode": "",
    "Nickname": "",
    "InjuryStatus": "",
    "InjuryDesc": "",
    "GfxId": 26,
    "Headshot": "",
    "IsStarting": true,
    "Initials": "",
    "TrackingId": "",
    "TeamId": "6",
    "Affiliate": "",
    "CloudHeadshotURL": "https://res.cloudinary.com/xfl-production/image/upload/v1668132138/xfl-prod/headshots/Jordan_Evans_20460.png",
    "SquadId": "",
    "College": "",
    "LeagueStatus": "",
    "Participated": true,
    "PreviousTeamId": ""
  },
  {
    "OfficialId": "21871",
    "VisOrHome": "Home",
    "JerseyNum": "28",
    "FirstName": "Brenden",
    "LastName": "Knox",
    "LastNameSuffix": "",
    "Position": "RB",
    "PositionLongName": "",
    "NAbbrev": "B. Knox",
    "Height": "5'10\"",
    "Weight": "215",
    "DOB": "10/10/1998",
    "POB": "",
    "Age": 24,
    "Hometown": "",
    "Country": "",
    "CountryCode": "",
    "Nickname": "",
    "InjuryStatus": "",
    "InjuryDesc": "",
    "GfxId": 28,
    "Headshot": "",
    "IsStarting": true,
    "Initials": "",
    "TrackingId": "",
    "TeamId": "6",
    "Affiliate": "",
    "CloudHeadshotURL": "",
    "SquadId": "",
    "College": "",
    "LeagueStatus": "",
    "Participated": true,
    "PreviousTeamId": ""
  },
  {
    "OfficialId": "20311",
    "VisOrHome": "Home",
    "JerseyNum": "32",
    "FirstName": "Qwynnterrio",
    "LastName": "Cole",
    "LastNameSuffix": "",
    "Position": "DB",
    "PositionLongName": "",
    "NAbbrev": "Q. Cole",
    "Height": "6'0\"",
    "Weight": "203",
    "DOB": "",
    "POB": "",
    "Hometown": "",
    "Country": "",
    "CountryCode": "",
    "Nickname": "",
    "InjuryStatus": "",
    "InjuryDesc": "",
    "GfxId": 32,
    "Headshot": "",
    "Initials": "",
    "TrackingId": "",
    "TeamId": "6",
    "Affiliate": "",
    "CloudHeadshotURL": "https://res.cloudinary.com/xfl-production/image/upload/v1668132138/xfl-prod/headshots/Qwynnterrio_Cole_20311.png",
    "SquadId": "",
    "College": "",
    "LeagueStatus": "",
    "Participated": true,
    "PreviousTeamId": ""
  },
  {
    "OfficialId": "22552",
    "VisOrHome": "Home",
    "JerseyNum": "33",
    "FirstName": "Alijah",
    "LastName": "Holder",
    "LastNameSuffix": "",
    "Position": "DB",
    "PositionLongName": "",
    "NAbbrev": "A. Holder",
    "Height": "6'2\"",
    "Weight": "197",
    "DOB": "",
    "POB": "",
    "Hometown": "",
    "Country": "",
    "CountryCode": "",
    "Nickname": "",
    "InjuryStatus": "",
    "InjuryDesc": "",
    "GfxId": 33,
    "Headshot": "",
    "IsStarting": true,
    "Initials": "",
    "TrackingId": "",
    "TeamId": "6",
    "Affiliate": "",
    "CloudHeadshotURL": "",
    "SquadId": "",
    "College": "",
    "LeagueStatus": "",
    "Participated": true,
    "PreviousTeamId": ""
  },
  {
    "OfficialId": "20878",
    "VisOrHome": "Home",
    "JerseyNum": "36",
    "FirstName": "Zafir",
    "LastName": "Kelly",
    "LastNameSuffix": "",
    "Position": "DB",
    "PositionLongName": "",
    "NAbbrev": "Z. Kelly",
    "Height": "5'11\"",
    "Weight": "178",
    "DOB": "",
    "POB": "",
    "Hometown": "",
    "Country": "",
    "CountryCode": "",
    "Nickname": "",
    "InjuryStatus": "",
    "InjuryDesc": "",
    "GfxId": 36,
    "Headshot": "",
    "Initials": "",
    "TrackingId": "",
    "TeamId": "6",
    "Affiliate": "",
    "CloudHeadshotURL": "https://res.cloudinary.com/xfl-production/image/upload/v1668132138/xfl-prod/headshots/Zafir_Kelly_20878.png",
    "SquadId": "",
    "College": "",
    "LeagueStatus": "",
    "Participated": true,
    "PreviousTeamId": ""
  },
  {
    "OfficialId": "21437",
    "VisOrHome": "Home",
    "JerseyNum": "43",
    "FirstName": "Emmanuel",
    "LastName": "Smith",
    "LastNameSuffix": "",
    "Position": "LB",
    "PositionLongName": "",
    "NAbbrev": "E. Smith",
    "Height": "6'1\"",
    "Weight": "235",
    "DOB": "7/25/1995",
    "POB": "",
    "Age": 27,
    "Hometown": "",
    "Country": "",
    "CountryCode": "",
    "Nickname": "",
    "InjuryStatus": "",
    "InjuryDesc": "",
    "GfxId": 43,
    "Headshot": "",
    "Initials": "",
    "TrackingId": "",
    "TeamId": "6",
    "Affiliate": "",
    "CloudHeadshotURL": "",
    "SquadId": "",
    "College": "",
    "LeagueStatus": "",
    "Participated": true,
    "PreviousTeamId": ""
  },
  {
    "OfficialId": "22017",
    "VisOrHome": "Home",
    "JerseyNum": "44",
    "FirstName": "Elijah",
    "LastName": "Ponder",
    "LastNameSuffix": "",
    "Position": "LB",
    "PositionLongName": "",
    "NAbbrev": "E. Ponder",
    "Height": "6'1\"",
    "Weight": "258",
    "DOB": "",
    "POB": "",
    "Hometown": "",
    "Country": "",
    "CountryCode": "",
    "Nickname": "",
    "InjuryStatus": "",
    "InjuryDesc": "",
    "GfxId": 44,
    "Headshot": "",
    "IsStarting": true,
    "Initials": "",
    "TrackingId": "",
    "TeamId": "6",
    "Affiliate": "",
    "CloudHeadshotURL": "",
    "SquadId": "",
    "College": "",
    "LeagueStatus": "",
    "Participated": true,
    "PreviousTeamId": ""
  },
  {
    "OfficialId": "20486",
    "VisOrHome": "Home",
    "JerseyNum": "45",
    "FirstName": "Thomas",
    "LastName": "Fletcher",
    "LastNameSuffix": "",
    "Position": "LS",
    "PositionLongName": "",
    "NAbbrev": "T. Fletcher",
    "Height": "6'0\"",
    "Weight": "236",
    "DOB": "",
    "POB": "",
    "Hometown": "",
    "Country": "",
    "CountryCode": "",
    "Nickname": "",
    "InjuryStatus": "",
    "InjuryDesc": "",
    "GfxId": 45,
    "Headshot": "",
    "Initials": "",
    "TrackingId": "",
    "TeamId": "6",
    "Affiliate": "",
    "CloudHeadshotURL": "https://res.cloudinary.com/xfl-production/image/upload/v1668132138/xfl-prod/headshots/Thomas_Fletcher_20486.png",
    "SquadId": "",
    "College": "",
    "LeagueStatus": "",
    "Participated": true,
    "PreviousTeamId": ""
  },
  {
    "OfficialId": "22630",
    "VisOrHome": "Home",
    "JerseyNum": "48",
    "FirstName": "Shareef",
    "LastName": "Miller",
    "LastNameSuffix": "",
    "Position": "LB",
    "PositionLongName": "",
    "NAbbrev": "S. Miller",
    "Height": "6'5\"",
    "Weight": "267",
    "DOB": "",
    "POB": "",
    "Hometown": "",
    "Country": "",
    "CountryCode": "",
    "Nickname": "",
    "InjuryStatus": "",
    "InjuryDesc": "",
    "GfxId": 48,
    "Headshot": "",
    "Initials": "",
    "TrackingId": "",
    "TeamId": "6",
    "Affiliate": "",
    "CloudHeadshotURL": "",
    "SquadId": "",
    "College": "",
    "LeagueStatus": "",
    "Participated": true,
    "PreviousTeamId": ""
  },
  {
    "OfficialId": "21178",
    "VisOrHome": "Home",
    "JerseyNum": "50",
    "FirstName": "Sama",
    "LastName": "Paama",
    "LastNameSuffix": "",
    "Position": "DL",
    "PositionLongName": "",
    "NAbbrev": "S. Paama",
    "Height": "6'4\"",
    "Weight": "348",
    "DOB": "",
    "POB": "",
    "Hometown": "",
    "Country": "",
    "CountryCode": "",
    "Nickname": "",
    "InjuryStatus": "",
    "InjuryDesc": "",
    "GfxId": 50,
    "Headshot": "",
    "Initials": "",
    "TrackingId": "",
    "TeamId": "6",
    "Affiliate": "",
    "CloudHeadshotURL": "https://res.cloudinary.com/xfl-production/image/upload/v1668132138/xfl-prod/headshots/Sama_Paama_21178.png",
    "SquadId": "",
    "College": "",
    "LeagueStatus": "",
    "Participated": true,
    "PreviousTeamId": ""
  },
  {
    "OfficialId": "21422",
    "VisOrHome": "Home",
    "JerseyNum": "51",
    "FirstName": "Tuzar",
    "LastName": "Skipper",
    "LastNameSuffix": "",
    "Position": "LB",
    "PositionLongName": "",
    "NAbbrev": "T. Skipper",
    "Height": "6'2\"",
    "Weight": "248",
    "DOB": "6/5/1995",
    "POB": "",
    "Age": 27,
    "Hometown": "",
    "Country": "",
    "CountryCode": "",
    "Nickname": "",
    "InjuryStatus": "",
    "InjuryDesc": "",
    "GfxId": 51,
    "Headshot": "",
    "Initials": "",
    "TrackingId": "",
    "TeamId": "6",
    "Affiliate": "",
    "CloudHeadshotURL": "https://res.cloudinary.com/xfl-production/image/upload/v1668132138/xfl-prod/headshots/Tuzar_Skipper_21422.png",
    "SquadId": "",
    "College": "",
    "LeagueStatus": "",
    "Participated": true,
    "PreviousTeamId": ""
  },
  {
    "OfficialId": "20760",
    "VisOrHome": "Home",
    "JerseyNum": "52",
    "FirstName": "Antwuan",
    "LastName": "Jackson",
    "LastNameSuffix": "",
    "Position": "DL",
    "PositionLongName": "",
    "NAbbrev": "A. Jackson",
    "Height": "6'2\"",
    "Weight": "298",
    "DOB": "",
    "POB": "",
    "Hometown": "",
    "Country": "",
    "CountryCode": "",
    "Nickname": "",
    "InjuryStatus": "",
    "InjuryDesc": "",
    "GfxId": 52,
    "Headshot": "",
    "IsStarting": true,
    "Initials": "",
    "TrackingId": "",
    "TeamId": "6",
    "Affiliate": "",
    "CloudHeadshotURL": "",
    "SquadId": "",
    "College": "",
    "LeagueStatus": "",
    "Participated": true,
    "PreviousTeamId": ""
  },
  {
    "OfficialId": "21172",
    "VisOrHome": "Home",
    "JerseyNum": "55",
    "FirstName": "Chris",
    "LastName": "Owens",
    "LastNameSuffix": "",
    "Position": "OL",
    "PositionLongName": "",
    "NAbbrev": "C. Owens",
    "Height": "6'2\"",
    "Weight": "300",
    "DOB": "",
    "POB": "",
    "Hometown": "",
    "Country": "",
    "CountryCode": "",
    "Nickname": "",
    "InjuryStatus": "",
    "InjuryDesc": "",
    "GfxId": 55,
    "Headshot": "",
    "IsStarting": true,
    "Initials": "",
    "TrackingId": "",
    "TeamId": "6",
    "Affiliate": "",
    "CloudHeadshotURL": "https://res.cloudinary.com/xfl-production/image/upload/v1668132138/xfl-prod/headshots/Chris_Owens_21172.png",
    "SquadId": "",
    "College": "",
    "LeagueStatus": "",
    "Participated": true,
    "PreviousTeamId": ""
  },
  {
    "OfficialId": "22584",
    "VisOrHome": "Home",
    "JerseyNum": "56",
    "FirstName": "Tejan",
    "LastName": "Koroma",
    "LastNameSuffix": "",
    "Position": "OL",
    "PositionLongName": "",
    "NAbbrev": "T. Koroma",
    "Height": "6'0\"",
    "Weight": "299",
    "DOB": "",
    "POB": "",
    "Hometown": "",
    "Country": "",
    "CountryCode": "",
    "Nickname": "",
    "InjuryStatus": "",
    "InjuryDesc": "",
    "GfxId": 56,
    "Headshot": "",
    "Initials": "",
    "TrackingId": "",
    "TeamId": "6",
    "Affiliate": "",
    "CloudHeadshotURL": "",
    "SquadId": "",
    "College": "",
    "LeagueStatus": "",
    "Participated": true,
    "PreviousTeamId": ""
  },
  {
    "OfficialId": "20466",
    "VisOrHome": "Home",
    "JerseyNum": "58",
    "FirstName": "Austin",
    "LastName": "Faoliu",
    "LastNameSuffix": "",
    "Position": "DL",
    "PositionLongName": "",
    "NAbbrev": "A. Faoliu",
    "Height": "6'3\"",
    "Weight": "287",
    "DOB": "",
    "POB": "",
    "Hometown": "",
    "Country": "",
    "CountryCode": "",
    "Nickname": "",
    "InjuryStatus": "",
    "InjuryDesc": "",
    "GfxId": 58,
    "Headshot": "",
    "IsStarting": true,
    "Initials": "",
    "TrackingId": "",
    "TeamId": "6",
    "Affiliate": "",
    "CloudHeadshotURL": "",
    "SquadId": "",
    "College": "",
    "LeagueStatus": "",
    "Participated": true,
    "PreviousTeamId": ""
  },
  {
    "OfficialId": "20573",
    "VisOrHome": "Home",
    "JerseyNum": "65",
    "FirstName": "Paul",
    "LastName": "Grattan",
    "LastNameSuffix": "",
    "Position": "OL",
    "PositionLongName": "",
    "NAbbrev": "P. Grattan",
    "Height": "6'3\"",
    "Weight": "299",
    "DOB": "8/28/1997",
    "POB": "",
    "Age": 25,
    "Hometown": "",
    "Country": "",
    "CountryCode": "",
    "Nickname": "",
    "InjuryStatus": "",
    "InjuryDesc": "",
    "GfxId": 65,
    "Headshot": "",
    "Initials": "",
    "Scratch": true,
    "TrackingId": "",
    "TeamId": "6",
    "Affiliate": "",
    "CloudHeadshotURL": "https://res.cloudinary.com/xfl-production/image/upload/v1668132138/xfl-prod/headshots/Paul_Grattan_20573.png",
    "SquadId": "",
    "College": "",
    "LeagueStatus": "",
    "PreviousTeamId": ""
  },
  {
    "OfficialId": "22883",
    "VisOrHome": "Home",
    "JerseyNum": "67",
    "FirstName": "Colin",
    "LastName": "Kelly",
    "LastNameSuffix": "",
    "Position": "OL",
    "PositionLongName": "",
    "NAbbrev": "C. Kelly",
    "Height": "6'5\"",
    "Weight": "298",
    "DOB": "",
    "POB": "",
    "Hometown": "",
    "Country": "",
    "CountryCode": "",
    "Nickname": "",
    "InjuryStatus": "",
    "InjuryDesc": "",
    "GfxId": 67,
    "Headshot": "",
    "IsStarting": true,
    "Initials": "",
    "TrackingId": "",
    "TeamId": "6",
    "Affiliate": "",
    "CloudHeadshotURL": "",
    "SquadId": "",
    "College": "",
    "LeagueStatus": "",
    "Participated": true,
    "PreviousTeamId": ""
  },
  {
    "OfficialId": "21649",
    "VisOrHome": "Home",
    "JerseyNum": "69",
    "FirstName": "Barry",
    "LastName": "Wesley",
    "LastNameSuffix": "",
    "Position": "OL",
    "PositionLongName": "",
    "NAbbrev": "B. Wesley",
    "Height": "6'6\"",
    "Weight": "312",
    "DOB": "",
    "POB": "",
    "Hometown": "",
    "Country": "",
    "CountryCode": "",
    "Nickname": "",
    "InjuryStatus": "",
    "InjuryDesc": "",
    "GfxId": 69,
    "Headshot": "",
    "Initials": "",
    "TrackingId": "",
    "TeamId": "6",
    "Affiliate": "",
    "CloudHeadshotURL": "",
    "SquadId": "",
    "College": "",
    "LeagueStatus": "",
    "Participated": true,
    "PreviousTeamId": ""
  },
  {
    "OfficialId": "21391",
    "VisOrHome": "Home",
    "JerseyNum": "70",
    "FirstName": "Josh",
    "LastName": "Seltzner",
    "LastNameSuffix": "",
    "Position": "OL",
    "PositionLongName": "",
    "NAbbrev": "J. Seltzner",
    "Height": "6'4\"",
    "Weight": "309",
    "DOB": "",
    "POB": "",
    "Hometown": "",
    "Country": "",
    "CountryCode": "",
    "Nickname": "",
    "InjuryStatus": "",
    "InjuryDesc": "",
    "GfxId": 70,
    "Headshot": "",
    "Initials": "",
    "TrackingId": "",
    "TeamId": "6",
    "Affiliate": "",
    "CloudHeadshotURL": "",
    "SquadId": "",
    "College": "",
    "LeagueStatus": "",
    "Participated": true,
    "PreviousTeamId": ""
  },
  {
    "OfficialId": "20794",
    "VisOrHome": "Home",
    "JerseyNum": "71",
    "FirstName": "Liam",
    "LastName": "Jimmons",
    "LastNameSuffix": "",
    "Position": "OL",
    "PositionLongName": "",
    "NAbbrev": "L. Jimmons",
    "Height": "6'5\"",
    "Weight": "320",
    "DOB": "",
    "POB": "",
    "Hometown": "",
    "Country": "",
    "CountryCode": "",
    "Nickname": "",
    "InjuryStatus": "",
    "InjuryDesc": "",
    "GfxId": 71,
    "Headshot": "",
    "IsStarting": true,
    "Initials": "",
    "TrackingId": "",
    "TeamId": "6",
    "Affiliate": "",
    "CloudHeadshotURL": "https://res.cloudinary.com/xfl-production/image/upload/v1668132138/xfl-prod/headshots/Liam_Jimmons_20794.png",
    "SquadId": "",
    "College": "",
    "LeagueStatus": "",
    "Participated": true,
    "PreviousTeamId": ""
  },
  {
    "OfficialId": "21059",
    "VisOrHome": "Home",
    "JerseyNum": "72",
    "FirstName": "Michal",
    "LastName": "Menet",
    "LastNameSuffix": "",
    "Position": "OL",
    "PositionLongName": "",
    "NAbbrev": "M. Menet",
    "Height": "6'4\"",
    "Weight": "301",
    "DOB": "8/8/1997",
    "POB": "",
    "Age": 25,
    "Hometown": "",
    "Country": "",
    "CountryCode": "",
    "Nickname": "",
    "InjuryStatus": "",
    "InjuryDesc": "",
    "GfxId": 72,
    "Headshot": "",
    "IsStarting": true,
    "Initials": "",
    "TrackingId": "",
    "TeamId": "6",
    "Affiliate": "",
    "CloudHeadshotURL": "",
    "SquadId": "",
    "College": "",
    "LeagueStatus": "",
    "Participated": true,
    "PreviousTeamId": ""
  },
  {
    "OfficialId": "22766",
    "VisOrHome": "Home",
    "JerseyNum": "73",
    "FirstName": "Jared",
    "LastName": "Thomas",
    "LastNameSuffix": "",
    "Position": "OL",
    "PositionLongName": "",
    "NAbbrev": "J. Thomas",
    "Height": "6'3\"",
    "Weight": "318",
    "DOB": "",
    "POB": "",
    "Hometown": "",
    "Country": "",
    "CountryCode": "",
    "Nickname": "",
    "InjuryStatus": "",
    "InjuryDesc": "",
    "GfxId": 73,
    "Headshot": "",
    "IsStarting": true,
    "Initials": "",
    "TrackingId": "",
    "TeamId": "6",
    "Affiliate": "",
    "CloudHeadshotURL": "",
    "SquadId": "",
    "College": "",
    "LeagueStatus": "",
    "Participated": true,
    "PreviousTeamId": ""
  },
  {
    "OfficialId": "20761",
    "VisOrHome": "Home",
    "JerseyNum": "80",
    "FirstName": "Blake",
    "LastName": "Jackson",
    "LastNameSuffix": "",
    "Position": "WR",
    "PositionLongName": "",
    "NAbbrev": "B. Jackson",
    "Height": "5'11\"",
    "Weight": "205",
    "DOB": "3/7/1994",
    "POB": "",
    "Age": 28,
    "Hometown": "",
    "Country": "",
    "CountryCode": "",
    "Nickname": "",
    "InjuryStatus": "",
    "InjuryDesc": "",
    "GfxId": 80,
    "Headshot": "",
    "IsStarting": true,
    "Initials": "",
    "TrackingId": "",
    "TeamId": "6",
    "Affiliate": "",
    "CloudHeadshotURL": "https://res.cloudinary.com/xfl-production/image/upload/v1668132138/xfl-prod/headshots/Blake_Jackson_20761.png",
    "SquadId": "",
    "College": "",
    "LeagueStatus": "",
    "Participated": true,
    "PreviousTeamId": ""
  },
  {
    "OfficialId": "21875",
    "VisOrHome": "Home",
    "JerseyNum": "86",
    "FirstName": "Kelvin",
    "LastName": "McKnight",
    "LastNameSuffix": "",
    "Position": "WR",
    "PositionLongName": "",
    "NAbbrev": "K. McKnight",
    "Height": "5'8\"",
    "Weight": "185",
    "DOB": "4/25/1997",
    "POB": "",
    "Age": 25,
    "Hometown": "",
    "Country": "",
    "CountryCode": "",
    "Nickname": "",
    "InjuryStatus": "",
    "InjuryDesc": "",
    "GfxId": 86,
    "Headshot": "",
    "Initials": "",
    "Scratch": true,
    "TrackingId": "",
    "TeamId": "6",
    "Affiliate": "",
    "CloudHeadshotURL": "",
    "SquadId": "",
    "College": "",
    "LeagueStatus": "",
    "PreviousTeamId": ""
  },
  {
    "OfficialId": "22306",
    "VisOrHome": "Home",
    "JerseyNum": "88",
    "FirstName": "Jordan",
    "LastName": "Veasy",
    "LastNameSuffix": "",
    "Position": "WR",
    "PositionLongName": "",
    "NAbbrev": "J. Veasy",
    "Height": "6'2\"",
    "Weight": "219",
    "DOB": "",
    "POB": "",
    "Hometown": "",
    "Country": "",
    "CountryCode": "",
    "Nickname": "",
    "InjuryStatus": "",
    "InjuryDesc": "",
    "GfxId": 88,
    "Headshot": "",
    "IsStarting": true,
    "Initials": "",
    "TrackingId": "",
    "TeamId": "6",
    "Affiliate": "",
    "CloudHeadshotURL": "",
    "SquadId": "",
    "College": "",
    "LeagueStatus": "",
    "Participated": true,
    "PreviousTeamId": ""
  },
  {
    "OfficialId": "21967",
    "VisOrHome": "Home",
    "JerseyNum": "89",
    "FirstName": "Charlie",
    "LastName": "Taumoepeau",
    "LastNameSuffix": "",
    "Position": "TE",
    "PositionLongName": "",
    "NAbbrev": "C. Taumoepeau",
    "Height": "6'2\"",
    "Weight": "240",
    "DOB": "",
    "POB": "",
    "Hometown": "",
    "Country": "",
    "CountryCode": "",
    "Nickname": "",
    "InjuryStatus": "",
    "InjuryDesc": "",
    "GfxId": 89,
    "Headshot": "",
    "Initials": "",
    "TrackingId": "",
    "TeamId": "6",
    "Affiliate": "",
    "CloudHeadshotURL": "",
    "SquadId": "",
    "College": "",
    "LeagueStatus": "",
    "Participated": true,
    "PreviousTeamId": ""
  },
  {
    "OfficialId": "21939",
    "VisOrHome": "Home",
    "JerseyNum": "92",
    "FirstName": "P.J.",
    "LastName": "Hall",
    "LastNameSuffix": "",
    "Position": "DL",
    "PositionLongName": "",
    "NAbbrev": "P. Hall",
    "Height": "6'0\"",
    "Weight": "308",
    "DOB": "4/5/1995",
    "POB": "",
    "Age": 27,
    "Hometown": "",
    "Country": "",
    "CountryCode": "",
    "Nickname": "",
    "InjuryStatus": "",
    "InjuryDesc": "",
    "GfxId": 92,
    "Headshot": "",
    "Initials": "",
    "TrackingId": "",
    "TeamId": "6",
    "Affiliate": "",
    "CloudHeadshotURL": "",
    "SquadId": "",
    "College": "",
    "LeagueStatus": "",
    "Participated": true,
    "PreviousTeamId": ""
  },
  {
    "OfficialId": "22025",
    "VisOrHome": "Home",
    "JerseyNum": "93",
    "FirstName": "Treyvon",
    "LastName": "Hester",
    "LastNameSuffix": "",
    "Position": "DL",
    "PositionLongName": "",
    "NAbbrev": "T. Hester",
    "Height": "6'2\"",
    "Weight": "300",
    "DOB": "9/21/1992",
    "POB": "",
    "Age": 30,
    "Hometown": "",
    "Country": "",
    "CountryCode": "",
    "Nickname": "",
    "InjuryStatus": "",
    "InjuryDesc": "",
    "GfxId": 93,
    "Headshot": "",
    "Initials": "",
    "Scratch": true,
    "TrackingId": "",
    "TeamId": "6",
    "Affiliate": "",
    "CloudHeadshotURL": "",
    "SquadId": "",
    "College": "",
    "LeagueStatus": "",
    "PreviousTeamId": ""
  },
  {
    "OfficialId": "21869",
    "VisOrHome": "Home",
    "JerseyNum": "96",
    "FirstName": "Daniel",
    "LastName": "Joseph",
    "LastNameSuffix": "",
    "Position": "DL",
    "PositionLongName": "",
    "NAbbrev": "D. Joseph",
    "Height": "6'2\"",
    "Weight": "261",
    "DOB": "",
    "POB": "",
    "Hometown": "",
    "Country": "",
    "CountryCode": "",
    "Nickname": "",
    "InjuryStatus": "",
    "InjuryDesc": "",
    "GfxId": 96,
    "Headshot": "",
    "Initials": "",
    "TrackingId": "",
    "TeamId": "6",
    "Affiliate": "",
    "CloudHeadshotURL": "https://res.cloudinary.com/xfl-production/image/upload/v1668132138/xfl-prod/headshots/Daniel_Joseph_21869.png",
    "SquadId": "",
    "College": "",
    "LeagueStatus": "",
    "Participated": true,
    "PreviousTeamId": ""
  },
  {
    "OfficialId": "20918",
    "VisOrHome": "Home",
    "JerseyNum": "97",
    "FirstName": "Niko",
    "LastName": "Lalos",
    "LastNameSuffix": "",
    "Position": "DL",
    "PositionLongName": "",
    "NAbbrev": "N. Lalos",
    "Height": "6'4\"",
    "Weight": "260",
    "DOB": "6/25/1997",
    "POB": "",
    "Age": 25,
    "Hometown": "",
    "Country": "",
    "CountryCode": "",
    "Nickname": "",
    "InjuryStatus": "",
    "InjuryDesc": "",
    "GfxId": 97,
    "Headshot": "",
    "IsStarting": true,
    "Initials": "",
    "TrackingId": "",
    "TeamId": "6",
    "Affiliate": "",
    "CloudHeadshotURL": "https://res.cloudinary.com/xfl-production/image/upload/v1668132138/xfl-prod/headshots/Niko_Lalos_20918.png",
    "SquadId": "",
    "College": "",
    "LeagueStatus": "",
    "Participated": true,
    "PreviousTeamId": ""
  },
  {
    "OfficialId": "22033",
    "VisOrHome": "Visitor",
    "JerseyNum": "0",
    "FirstName": "Kareem",
    "LastName": "Walker",
    "LastNameSuffix": "",
    "Position": "RB",
    "PositionLongName": "",
    "NAbbrev": "K. Walker",
    "Height": "6'0\"",
    "Weight": "209",
    "DOB": "",
    "POB": "",
    "Hometown": "",
    "Country": "",
    "CountryCode": "",
    "Nickname": "",
    "InjuryStatus": "",
    "InjuryDesc": "",
    "Headshot": "",
    "IsStarting": true,
    "Initials": "",
    "TrackingId": "",
    "TeamId": "5",
    "Affiliate": "",
    "CloudHeadshotURL": "",
    "SquadId": "",
    "College": "",
    "LeagueStatus": "",
    "Participated": true,
    "PreviousTeamId": ""
  },
  {
    "OfficialId": "20615",
    "VisOrHome": "Visitor",
    "JerseyNum": "1",
    "FirstName": "Elijah",
    "LastName": "Hamilton",
    "LastNameSuffix": "",
    "Position": "DB",
    "PositionLongName": "",
    "NAbbrev": "E. Hamilton",
    "Height": "6'1\"",
    "Weight": "211",
    "DOB": "",
    "POB": "",
    "Hometown": "",
    "Country": "",
    "CountryCode": "",
    "Nickname": "",
    "InjuryStatus": "",
    "InjuryDesc": "",
    "GfxId": 1,
    "Headshot": "",
    "IsStarting": true,
    "Initials": "",
    "TrackingId": "",
    "TeamId": "5",
    "Affiliate": "",
    "CloudHeadshotURL": "https://res.cloudinary.com/xfl-production/image/upload/v1668132138/xfl-prod/headshots/Elijah_Hamilton_20615.png",
    "SquadId": "",
    "College": "",
    "LeagueStatus": "",
    "PreviousTeamId": ""
  },
  {
    "OfficialId": "22008",
    "VisOrHome": "Visitor",
    "JerseyNum": "2",
    "FirstName": "Donald",
    "LastName": "Hageman",
    "LastNameSuffix": "",
    "Position": "K",
    "PositionLongName": "",
    "NAbbrev": "D. Hageman",
    "Height": "6'1\"",
    "Weight": "177",
    "DOB": "",
    "POB": "",
    "Hometown": "",
    "Country": "",
    "CountryCode": "",
    "Nickname": "",
    "InjuryStatus": "",
    "InjuryDesc": "",
    "GfxId": 2,
    "Headshot": "",
    "Initials": "",
    "TrackingId": "",
    "TeamId": "5",
    "Affiliate": "",
    "CloudHeadshotURL": "",
    "SquadId": "",
    "College": "",
    "LeagueStatus": "",
    "Participated": true,
    "PreviousTeamId": ""
  },
  {
    "OfficialId": "20058",
    "VisOrHome": "Visitor",
    "JerseyNum": "3",
    "FirstName": "Marcell",
    "LastName": "Ateman",
    "LastNameSuffix": "",
    "Position": "WR",
    "PositionLongName": "",
    "NAbbrev": "M. Ateman",
    "Height": "6'4\"",
    "Weight": "215",
    "DOB": "9/16/1994",
    "POB": "",
    "Age": 28,
    "Hometown": "",
    "Country": "",
    "CountryCode": "",
    "Nickname": "",
    "InjuryStatus": "",
    "InjuryDesc": "",
    "GfxId": 3,
    "Headshot": "",
    "IsStarting": true,
    "Initials": "",
    "TrackingId": "",
    "TeamId": "5",
    "Affiliate": "",
    "CloudHeadshotURL": "",
    "SquadId": "",
    "College": "",
    "LeagueStatus": "",
    "Participated": true,
    "PreviousTeamId": ""
  },
  {
    "OfficialId": "21667",
    "VisOrHome": "Visitor",
    "JerseyNum": "5",
    "FirstName": "Manny",
    "LastName": "Wilkins",
    "LastNameSuffix": "",
    "Position": "QB",
    "PositionLongName": "",
    "NAbbrev": "M. Wilkins",
    "Height": "6'2\"",
    "Weight": "193",
    "DOB": "",
    "POB": "",
    "Hometown": "",
    "Country": "",
    "CountryCode": "",
    "Nickname": "",
    "InjuryStatus": "",
    "InjuryDesc": "",
    "GfxId": 5,
    "Headshot": "",
    "Initials": "",
    "Scratch": true,
    "TrackingId": "",
    "TeamId": "5",
    "Affiliate": "",
    "CloudHeadshotURL": "https://res.cloudinary.com/xfl-production/image/upload/v1668132138/xfl-prod/headshots/Manny_Wilkins_21667.png",
    "SquadId": "",
    "College": "",
    "LeagueStatus": "",
    "PreviousTeamId": ""
  },
  {
    "OfficialId": "21678",
    "VisOrHome": "Visitor",
    "JerseyNum": "6",
    "FirstName": "Lakiem",
    "LastName": "Williams",
    "LastNameSuffix": "",
    "Position": "LB",
    "PositionLongName": "",
    "NAbbrev": "L. Williams",
    "Height": "5'11\"",
    "Weight": "233",
    "DOB": "8/18/1997",
    "POB": "",
    "Age": 25,
    "Hometown": "",
    "Country": "",
    "CountryCode": "",
    "Nickname": "",
    "InjuryStatus": "",
    "InjuryDesc": "",
    "GfxId": 6,
    "Headshot": "",
    "IsStarting": true,
    "Initials": "",
    "TrackingId": "",
    "TeamId": "5",
    "Affiliate": "",
    "CloudHeadshotURL": "",
    "SquadId": "",
    "College": "",
    "LeagueStatus": "",
    "Participated": true,
    "PreviousTeamId": ""
  },
  {
    "OfficialId": "21862",
    "VisOrHome": "Visitor",
    "JerseyNum": "8",
    "FirstName": "Mike",
    "LastName": "Hampton",
    "LastNameSuffix": "",
    "Position": "DB",
    "PositionLongName": "",
    "NAbbrev": "M. Hampton",
    "Height": "5'11\"",
    "Weight": "186",
    "DOB": "12/8/1997",
    "POB": "",
    "Age": 25,
    "Hometown": "",
    "Country": "",
    "CountryCode": "",
    "Nickname": "",
    "InjuryStatus": "",
    "InjuryDesc": "",
    "GfxId": 8,
    "Headshot": "",
    "Initials": "",
    "TrackingId": "",
    "TeamId": "5",
    "Affiliate": "",
    "CloudHeadshotURL": "",
    "SquadId": "",
    "College": "",
    "LeagueStatus": "",
    "Participated": true,
    "PreviousTeamId": ""
  },
  {
    "OfficialId": "20651",
    "VisOrHome": "Visitor",
    "JerseyNum": "9",
    "FirstName": "Jovani",
    "LastName": "Haskins",
    "LastNameSuffix": "",
    "Position": "TE",
    "PositionLongName": "",
    "NAbbrev": "J. Haskins",
    "Height": "6'4\"",
    "Weight": "252",
    "DOB": "",
    "POB": "",
    "Hometown": "",
    "Country": "",
    "CountryCode": "",
    "Nickname": "",
    "InjuryStatus": "",
    "InjuryDesc": "",
    "GfxId": 9,
    "Headshot": "",
    "Initials": "",
    "TrackingId": "",
    "TeamId": "5",
    "Affiliate": "",
    "CloudHeadshotURL": "https://res.cloudinary.com/xfl-production/image/upload/v1668132138/xfl-prod/headshots/Jovani_Haskins_20651.png",
    "SquadId": "",
    "College": "",
    "LeagueStatus": "",
    "Participated": true,
    "PreviousTeamId": ""
  },
  {
    "OfficialId": "22026",
    "VisOrHome": "Visitor",
    "JerseyNum": "10",
    "FirstName": "A. J.",
    "LastName": "McCarron",
    "LastNameSuffix": "",
    "Position": "QB",
    "PositionLongName": "",
    "NAbbrev": "A. McCarron",
    "Height": "6'3\"",
    "Weight": "220",
    "DOB": "9/13/1990",
    "POB": "",
    "Age": 32,
    "Hometown": "",
    "Country": "",
    "CountryCode": "",
    "Nickname": "",
    "InjuryStatus": "",
    "InjuryDesc": "",
    "GfxId": 10,
    "Headshot": "",
    "IsStarting": true,
    "Initials": "",
    "TrackingId": "",
    "TeamId": "5",
    "Affiliate": "",
    "CloudHeadshotURL": "",
    "SquadId": "",
    "College": "",
    "LeagueStatus": "",
    "Participated": true,
    "PreviousTeamId": ""
  },
  {
    "OfficialId": "21822",
    "VisOrHome": "Visitor",
    "JerseyNum": "11",
    "FirstName": "Darrius",
    "LastName": "Shepherd",
    "LastNameSuffix": "",
    "Position": "WR",
    "PositionLongName": "",
    "NAbbrev": "D. Shepherd",
    "Height": "5'10\"",
    "Weight": "186",
    "DOB": "11/1/1995",
    "POB": "",
    "Age": 27,
    "Hometown": "",
    "Country": "",
    "CountryCode": "",
    "Nickname": "",
    "InjuryStatus": "",
    "InjuryDesc": "",
    "GfxId": 11,
    "Headshot": "",
    "IsStarting": true,
    "Initials": "",
    "TrackingId": "",
    "TeamId": "5",
    "Affiliate": "",
    "CloudHeadshotURL": "",
    "SquadId": "",
    "College": "",
    "LeagueStatus": "",
    "Participated": true,
    "PreviousTeamId": ""
  },
  {
    "OfficialId": "22038",
    "VisOrHome": "Visitor",
    "JerseyNum": "12",
    "FirstName": "Gary",
    "LastName": "Jennings",
    "LastNameSuffix": "",
    "Position": "WR",
    "PositionLongName": "",
    "NAbbrev": "G. Jennings",
    "Height": "6'1\"",
    "Weight": "216",
    "DOB": "",
    "POB": "",
    "Hometown": "",
    "Country": "",
    "CountryCode": "",
    "Nickname": "",
    "InjuryStatus": "",
    "InjuryDesc": "",
    "GfxId": 12,
    "Headshot": "",
    "Initials": "",
    "TrackingId": "",
    "TeamId": "5",
    "Affiliate": "",
    "CloudHeadshotURL": "",
    "SquadId": "",
    "College": "",
    "LeagueStatus": "",
    "Participated": true,
    "PreviousTeamId": ""
  },
  {
    "OfficialId": "21263",
    "VisOrHome": "Visitor",
    "JerseyNum": "13",
    "FirstName": "Austin",
    "LastName": "Proehl",
    "LastNameSuffix": "",
    "Position": "WR",
    "PositionLongName": "",
    "NAbbrev": "A. Proehl",
    "Height": "5'9\"",
    "Weight": "179",
    "DOB": "10/11/1995",
    "POB": "",
    "Age": 27,
    "Hometown": "",
    "Country": "",
    "CountryCode": "",
    "Nickname": "",
    "InjuryStatus": "",
    "InjuryDesc": "",
    "GfxId": 13,
    "Headshot": "",
    "IsStarting": true,
    "Initials": "",
    "TrackingId": "",
    "TeamId": "5",
    "Affiliate": "",
    "CloudHeadshotURL": "https://res.cloudinary.com/xfl-production/image/upload/v1668132138/xfl-prod/headshots/Austin_Proehl_21263.png",
    "SquadId": "",
    "College": "",
    "LeagueStatus": "",
    "Participated": true,
    "PreviousTeamId": ""
  },
  {
    "OfficialId": "21558",
    "VisOrHome": "Visitor",
    "JerseyNum": "14",
    "FirstName": "Nick",
    "LastName": "Tiano",
    "LastNameSuffix": "",
    "Position": "QB",
    "PositionLongName": "",
    "NAbbrev": "N. Tiano",
    "Height": "6'4\"",
    "Weight": "236",
    "DOB": "12/10/1996",
    "POB": "",
    "Age": 26,
    "Hometown": "",
    "Country": "",
    "CountryCode": "",
    "Nickname": "",
    "InjuryStatus": "",
    "InjuryDesc": "",
    "GfxId": 14,
    "Headshot": "",
    "Initials": "",
    "TrackingId": "",
    "TeamId": "5",
    "Affiliate": "",
    "CloudHeadshotURL": "https://res.cloudinary.com/xfl-production/image/upload/v1668132138/xfl-prod/headshots/Nick_Tiano_21558.png",
    "SquadId": "",
    "College": "",
    "LeagueStatus": "",
    "PreviousTeamId": ""
  },
  {
    "OfficialId": "20249",
    "VisOrHome": "Visitor",
    "JerseyNum": "15",
    "FirstName": "George",
    "LastName": "Campbell",
    "LastNameSuffix": "",
    "Position": "WR",
    "PositionLongName": "",
    "NAbbrev": "G. Campbell",
    "Height": "6'2\"",
    "Weight": "207",
    "DOB": "10/27/1996",
    "POB": "",
    "Age": 26,
    "Hometown": "",
    "Country": "",
    "CountryCode": "",
    "Nickname": "",
    "InjuryStatus": "",
    "InjuryDesc": "",
    "GfxId": 15,
    "Headshot": "",
    "Initials": "",
    "TrackingId": "",
    "TeamId": "5",
    "Affiliate": "",
    "CloudHeadshotURL": "https://res.cloudinary.com/xfl-production/image/upload/v1668132138/xfl-prod/headshots/George_Campbell_20249.png",
    "SquadId": "",
    "College": "",
    "LeagueStatus": "",
    "Participated": true,
    "PreviousTeamId": ""
  },
  {
    "OfficialId": "20704",
    "VisOrHome": "Visitor",
    "JerseyNum": "16",
    "FirstName": "Sterling",
    "LastName": "Hofrichter",
    "LastNameSuffix": "",
    "Position": "P",
    "PositionLongName": "",
    "NAbbrev": "S. Hofrichter",
    "Height": "5'9\"",
    "Weight": "196",
    "DOB": "12/5/1996",
    "POB": "",
    "Age": 26,
    "Hometown": "",
    "Country": "",
    "CountryCode": "",
    "Nickname": "",
    "InjuryStatus": "",
    "InjuryDesc": "",
    "GfxId": 16,
    "Headshot": "",
    "Initials": "",
    "TrackingId": "",
    "TeamId": "5",
    "Affiliate": "",
    "CloudHeadshotURL": "",
    "SquadId": "",
    "College": "",
    "LeagueStatus": "",
    "Participated": true,
    "PreviousTeamId": ""
  },
  {
    "OfficialId": "21842",
    "VisOrHome": "Visitor",
    "JerseyNum": "17",
    "FirstName": "Jonathan",
    "LastName": "Alexander",
    "LastNameSuffix": "",
    "Position": "DB",
    "PositionLongName": "",
    "NAbbrev": "J. Alexander",
    "Height": "6'2\"",
    "Weight": "217",
    "DOB": "9/27/1999",
    "POB": "",
    "Age": 23,
    "Hometown": "",
    "Country": "",
    "CountryCode": "",
    "Nickname": "",
    "InjuryStatus": "",
    "InjuryDesc": "",
    "GfxId": 17,
    "Headshot": "",
    "Initials": "",
    "TrackingId": "",
    "TeamId": "5",
    "Affiliate": "",
    "CloudHeadshotURL": "https://res.cloudinary.com/xfl-production/image/upload/v1668132138/xfl-prod/headshots/Jonathan_Alexander_21842.png",
    "SquadId": "",
    "College": "",
    "LeagueStatus": "",
    "Participated": true,
    "PreviousTeamId": ""
  },
  {
    "OfficialId": "21856",
    "VisOrHome": "Visitor",
    "JerseyNum": "21",
    "FirstName": "Mataeo",
    "LastName": "Durant",
    "LastNameSuffix": "",
    "Position": "RB",
    "PositionLongName": "",
    "NAbbrev": "M. Durant",
    "Height": "5'11\"",
    "Weight": "196",
    "DOB": "",
    "POB": "",
    "Hometown": "",
    "Country": "",
    "CountryCode": "",
    "Nickname": "",
    "InjuryStatus": "",
    "InjuryDesc": "",
    "GfxId": 21,
    "Headshot": "",
    "Initials": "",
    "TrackingId": "",
    "TeamId": "5",
    "Affiliate": "",
    "CloudHeadshotURL": "",
    "SquadId": "",
    "College": "",
    "LeagueStatus": "",
    "Participated": true,
    "PreviousTeamId": ""
  },
  {
    "OfficialId": "21081",
    "VisOrHome": "Visitor",
    "JerseyNum": "22",
    "FirstName": "Steven",
    "LastName": "Mitchell",
    "LastNameSuffix": "",
    "Position": "WR",
    "PositionLongName": "",
    "NAbbrev": "S. Mitchell",
    "Height": "5'10\"",
    "Weight": "188",
    "DOB": "5/2/1994",
    "POB": "",
    "Age": 28,
    "Hometown": "",
    "Country": "",
    "CountryCode": "",
    "Nickname": "",
    "InjuryStatus": "",
    "InjuryDesc": "",
    "GfxId": 22,
    "Headshot": "",
    "Initials": "",
    "TrackingId": "",
    "TeamId": "5",
    "Affiliate": "",
    "CloudHeadshotURL": "https://res.cloudinary.com/xfl-production/image/upload/v1668132138/xfl-prod/headshots/Steven_Mitchell_21081.png",
    "SquadId": "",
    "College": "",
    "LeagueStatus": "",
    "Participated": true,
    "PreviousTeamId": ""
  },
  {
    "OfficialId": "20688",
    "VisOrHome": "Visitor",
    "JerseyNum": "23",
    "FirstName": "Brian",
    "LastName": "Hill",
    "LastNameSuffix": "",
    "Position": "RB",
    "PositionLongName": "",
    "NAbbrev": "B. Hill",
    "Height": "6'1\"",
    "Weight": "219",
    "DOB": "11/9/1995",
    "POB": "",
    "Age": 27,
    "Hometown": "",
    "Country": "",
    "CountryCode": "",
    "Nickname": "",
    "InjuryStatus": "",
    "InjuryDesc": "",
    "GfxId": 23,
    "Headshot": "",
    "Initials": "",
    "Scratch": true,
    "TrackingId": "",
    "TeamId": "5",
    "Affiliate": "",
    "CloudHeadshotURL": "",
    "SquadId": "",
    "College": "",
    "LeagueStatus": "",
    "PreviousTeamId": ""
  },
  {
    "OfficialId": "22870",
    "VisOrHome": "Visitor",
    "JerseyNum": "24",
    "FirstName": "Lavert",
    "LastName": "Hill",
    "LastNameSuffix": "",
    "Position": "DB",
    "PositionLongName": "",
    "NAbbrev": "L. Hill",
    "Height": "5'11\"",
    "Weight": "182",
    "DOB": "",
    "POB": "",
    "Hometown": "",
    "Country": "",
    "CountryCode": "",
    "Nickname": "",
    "InjuryStatus": "",
    "InjuryDesc": "",
    "GfxId": 24,
    "Headshot": "",
    "Initials": "",
    "TrackingId": "",
    "TeamId": "5",
    "Affiliate": "",
    "CloudHeadshotURL": "",
    "SquadId": "",
    "College": "",
    "LeagueStatus": "",
    "Participated": true,
    "PreviousTeamId": ""
  },
  {
    "OfficialId": "20385",
    "VisOrHome": "Visitor",
    "JerseyNum": "25",
    "FirstName": "Lukas",
    "LastName": "Denis",
    "LastNameSuffix": "",
    "Position": "DB",
    "PositionLongName": "",
    "NAbbrev": "L. Denis",
    "Height": "5'11\"",
    "Weight": "190",
    "DOB": "",
    "POB": "",
    "Hometown": "",
    "Country": "",
    "CountryCode": "",
    "Nickname": "",
    "InjuryStatus": "",
    "InjuryDesc": "",
    "GfxId": 25,
    "Headshot": "",
    "Initials": "",
    "TrackingId": "",
    "TeamId": "5",
    "Affiliate": "",
    "CloudHeadshotURL": "https://res.cloudinary.com/xfl-production/image/upload/v1668132138/xfl-prod/headshots/Lukas_Denis_20385.png",
    "SquadId": "",
    "College": "",
    "LeagueStatus": "",
    "Participated": true,
    "PreviousTeamId": ""
  },
  {
    "OfficialId": "22352",
    "VisOrHome": "Visitor",
    "JerseyNum": "26",
    "FirstName": "Nate",
    "LastName": "Meadors",
    "LastNameSuffix": "",
    "Position": "DB",
    "PositionLongName": "",
    "NAbbrev": "N. Meadors",
    "Height": "5'11\"",
    "Weight": "192",
    "DOB": "2/13/1997",
    "POB": "",
    "Age": 26,
    "Hometown": "",
    "Country": "",
    "CountryCode": "",
    "Nickname": "",
    "InjuryStatus": "",
    "InjuryDesc": "",
    "GfxId": 26,
    "Headshot": "",
    "IsStarting": true,
    "Initials": "",
    "TrackingId": "",
    "TeamId": "5",
    "Affiliate": "",
    "CloudHeadshotURL": "",
    "SquadId": "",
    "College": "",
    "LeagueStatus": "",
    "Participated": true,
    "PreviousTeamId": ""
  },
  {
    "OfficialId": "21340",
    "VisOrHome": "Visitor",
    "JerseyNum": "27",
    "FirstName": "Mike",
    "LastName": "Rose",
    "LastNameSuffix": "",
    "Position": "LB",
    "PositionLongName": "",
    "NAbbrev": "M. Rose",
    "Height": "6'3\"",
    "Weight": "243",
    "DOB": "",
    "POB": "",
    "Hometown": "",
    "Country": "",
    "CountryCode": "",
    "Nickname": "",
    "InjuryStatus": "",
    "InjuryDesc": "",
    "GfxId": 27,
    "Headshot": "",
    "Initials": "",
    "TrackingId": "",
    "TeamId": "5",
    "Affiliate": "",
    "CloudHeadshotURL": "https://res.cloudinary.com/xfl-production/image/upload/v1668132138/xfl-prod/headshots/Mike_Rose_21340.png",
    "SquadId": "",
    "College": "",
    "LeagueStatus": "",
    "Participated": true,
    "PreviousTeamId": ""
  },
  {
    "OfficialId": "20381",
    "VisOrHome": "Visitor",
    "JerseyNum": "28",
    "FirstName": "Ben",
    "LastName": "DeLuca",
    "LastNameSuffix": "",
    "Position": "DB",
    "PositionLongName": "",
    "NAbbrev": "B. DeLuca",
    "Height": "6'1\"",
    "Weight": "202",
    "DOB": "4/9/1998",
    "POB": "",
    "Age": 24,
    "Hometown": "",
    "Country": "",
    "CountryCode": "",
    "Nickname": "",
    "InjuryStatus": "",
    "InjuryDesc": "",
    "GfxId": 28,
    "Headshot": "",
    "IsStarting": true,
    "Initials": "",
    "TrackingId": "",
    "TeamId": "5",
    "Affiliate": "",
    "CloudHeadshotURL": "",
    "SquadId": "",
    "College": "",
    "LeagueStatus": "",
    "Participated": true,
    "PreviousTeamId": ""
  },
  {
    "OfficialId": "21870",
    "VisOrHome": "Visitor",
    "JerseyNum": "29",
    "FirstName": "Silas",
    "LastName": "Kelly",
    "LastNameSuffix": "",
    "Position": "LB",
    "PositionLongName": "",
    "NAbbrev": "S. Kelly",
    "Height": "6'3\"",
    "Weight": "229",
    "DOB": "",
    "POB": "",
    "Hometown": "",
    "Country": "",
    "CountryCode": "",
    "Nickname": "",
    "InjuryStatus": "",
    "InjuryDesc": "",
    "GfxId": 29,
    "Headshot": "",
    "Initials": "",
    "TrackingId": "",
    "TeamId": "5",
    "Affiliate": "",
    "CloudHeadshotURL": "https://res.cloudinary.com/xfl-production/image/upload/v1668132138/xfl-prod/headshots/Silas_Kelly_21870.png",
    "SquadId": "",
    "College": "",
    "LeagueStatus": "",
    "Participated": true,
    "PreviousTeamId": ""
  },
  {
    "OfficialId": "22297",
    "VisOrHome": "Visitor",
    "JerseyNum": "33",
    "FirstName": "Tre",
    "LastName": "Watson",
    "LastNameSuffix": "",
    "Position": "LB",
    "PositionLongName": "",
    "NAbbrev": "T. Watson",
    "Height": "6'2\"",
    "Weight": "242",
    "DOB": "7/5/1996",
    "POB": "",
    "Age": 26,
    "Hometown": "",
    "Country": "",
    "CountryCode": "",
    "Nickname": "",
    "InjuryStatus": "",
    "InjuryDesc": "",
    "GfxId": 33,
    "Headshot": "",
    "Initials": "",
    "TrackingId": "",
    "TeamId": "5",
    "Affiliate": "",
    "CloudHeadshotURL": "",
    "SquadId": "",
    "College": "",
    "LeagueStatus": "",
    "Participated": true,
    "PreviousTeamId": ""
  },
  {
    "OfficialId": "21389",
    "VisOrHome": "Visitor",
    "JerseyNum": "38",
    "FirstName": "Brandon",
    "LastName": "Sebastian",
    "LastNameSuffix": "",
    "Position": "DB",
    "PositionLongName": "",
    "NAbbrev": "B. Sebastian",
    "Height": "6'0\"",
    "Weight": "182",
    "DOB": "",
    "POB": "",
    "Hometown": "",
    "Country": "",
    "CountryCode": "",
    "Nickname": "",
    "InjuryStatus": "",
    "InjuryDesc": "",
    "GfxId": 38,
    "Headshot": "",
    "IsStarting": true,
    "Initials": "",
    "TrackingId": "",
    "TeamId": "5",
    "Affiliate": "",
    "CloudHeadshotURL": "https://res.cloudinary.com/xfl-production/image/upload/v1668132138/xfl-prod/headshots/Brandon_Sebastian_21389.png",
    "SquadId": "",
    "College": "",
    "LeagueStatus": "",
    "Participated": true,
    "PreviousTeamId": ""
  },
  {
    "OfficialId": "22336",
    "VisOrHome": "Visitor",
    "JerseyNum": "39",
    "FirstName": "Chris",
    "LastName": "Cooper",
    "LastNameSuffix": "",
    "Position": "DB",
    "PositionLongName": "",
    "NAbbrev": "C. Cooper",
    "Height": "5'10\"",
    "Weight": "202",
    "DOB": "3/17/1994",
    "POB": "",
    "Age": 28,
    "Hometown": "",
    "Country": "",
    "CountryCode": "",
    "Nickname": "",
    "InjuryStatus": "",
    "InjuryDesc": "",
    "GfxId": 39,
    "Headshot": "",
    "IsStarting": true,
    "Initials": "",
    "TrackingId": "",
    "TeamId": "5",
    "Affiliate": "",
    "CloudHeadshotURL": "",
    "SquadId": "",
    "College": "",
    "LeagueStatus": "",
    "Participated": true,
    "PreviousTeamId": ""
  },
  {
    "OfficialId": "22012",
    "VisOrHome": "Visitor",
    "JerseyNum": "47",
    "FirstName": "Alexander",
    "LastName": "Matheson",
    "LastNameSuffix": "",
    "Position": "LS",
    "PositionLongName": "",
    "NAbbrev": "A. Matheson",
    "Height": "6'5\"",
    "Weight": "245",
    "DOB": "",
    "POB": "",
    "Hometown": "",
    "Country": "",
    "CountryCode": "",
    "Nickname": "",
    "InjuryStatus": "",
    "InjuryDesc": "",
    "GfxId": 47,
    "Headshot": "",
    "Initials": "",
    "TrackingId": "",
    "TeamId": "5",
    "Affiliate": "",
    "CloudHeadshotURL": "",
    "SquadId": "",
    "College": "",
    "LeagueStatus": "",
    "Participated": true,
    "PreviousTeamId": ""
  },
  {
    "OfficialId": "20647",
    "VisOrHome": "Visitor",
    "JerseyNum": "51",
    "FirstName": "Willie",
    "LastName": "Harvey",
    "LastNameSuffix": "",
    "Position": "LB",
    "PositionLongName": "",
    "NAbbrev": "W. Harvey",
    "Height": "5'11\"",
    "Weight": "229",
    "DOB": "",
    "POB": "",
    "Hometown": "",
    "Country": "",
    "CountryCode": "",
    "Nickname": "",
    "InjuryStatus": "",
    "InjuryDesc": "",
    "GfxId": 51,
    "Headshot": "",
    "IsStarting": true,
    "Initials": "",
    "TrackingId": "",
    "TeamId": "5",
    "Affiliate": "",
    "CloudHeadshotURL": "",
    "SquadId": "",
    "College": "",
    "LeagueStatus": "",
    "Participated": true,
    "PreviousTeamId": ""
  },
  {
    "OfficialId": "21833",
    "VisOrHome": "Visitor",
    "JerseyNum": "53",
    "FirstName": "Carson",
    "LastName": "Wells",
    "LastNameSuffix": "",
    "Position": "LB",
    "PositionLongName": "",
    "NAbbrev": "C. Wells",
    "Height": "6'2\"",
    "Weight": "241",
    "DOB": "",
    "POB": "",
    "Hometown": "",
    "Country": "",
    "CountryCode": "",
    "Nickname": "",
    "InjuryStatus": "",
    "InjuryDesc": "",
    "GfxId": 53,
    "Headshot": "",
    "IsStarting": true,
    "Initials": "",
    "TrackingId": "",
    "TeamId": "5",
    "Affiliate": "",
    "CloudHeadshotURL": "",
    "SquadId": "",
    "College": "",
    "LeagueStatus": "",
    "Participated": true,
    "PreviousTeamId": ""
  },
  {
    "OfficialId": "22800",
    "VisOrHome": "Visitor",
    "JerseyNum": "55",
    "FirstName": "Dallas",
    "LastName": "Warmack",
    "LastNameSuffix": "",
    "Position": "OL",
    "PositionLongName": "",
    "NAbbrev": "D. Warmack",
    "Height": "6'2\"",
    "Weight": "310",
    "DOB": "",
    "POB": "",
    "Hometown": "",
    "Country": "",
    "CountryCode": "",
    "Nickname": "",
    "InjuryStatus": "",
    "InjuryDesc": "",
    "GfxId": 55,
    "Headshot": "",
    "Initials": "",
    "TrackingId": "",
    "TeamId": "5",
    "Affiliate": "",
    "CloudHeadshotURL": "",
    "SquadId": "",
    "College": "",
    "LeagueStatus": "",
    "Participated": true,
    "PreviousTeamId": ""
  },
  {
    "OfficialId": "22503",
    "VisOrHome": "Visitor",
    "JerseyNum": "56",
    "FirstName": "Travis",
    "LastName": "Feeney",
    "LastNameSuffix": "",
    "Position": "LB",
    "PositionLongName": "",
    "NAbbrev": "T. Feeney",
    "Height": "6'4\"",
    "Weight": "259",
    "DOB": "",
    "POB": "",
    "Hometown": "",
    "Country": "",
    "CountryCode": "",
    "Nickname": "",
    "InjuryStatus": "",
    "InjuryDesc": "",
    "GfxId": 56,
    "Headshot": "",
    "Initials": "",
    "Scratch": true,
    "TrackingId": "",
    "TeamId": "5",
    "Affiliate": "",
    "CloudHeadshotURL": "",
    "SquadId": "",
    "College": "",
    "LeagueStatus": "",
    "PreviousTeamId": ""
  },
  {
    "OfficialId": "21183",
    "VisOrHome": "Visitor",
    "JerseyNum": "61",
    "FirstName": "Mike",
    "LastName": "Panasiuk",
    "LastNameSuffix": "",
    "Position": "OL",
    "PositionLongName": "",
    "NAbbrev": "M. Panasiuk",
    "Height": "6'3\"",
    "Weight": "300",
    "DOB": "10/13/1997",
    "POB": "",
    "Age": 25,
    "Hometown": "",
    "Country": "",
    "CountryCode": "",
    "Nickname": "",
    "InjuryStatus": "",
    "InjuryDesc": "",
    "GfxId": 61,
    "Headshot": "",
    "IsStarting": true,
    "Initials": "",
    "TrackingId": "",
    "TeamId": "5",
    "Affiliate": "",
    "CloudHeadshotURL": "",
    "SquadId": "",
    "College": "",
    "LeagueStatus": "",
    "Participated": true,
    "PreviousTeamId": ""
  },
  {
    "OfficialId": "21165",
    "VisOrHome": "Visitor",
    "JerseyNum": "67",
    "FirstName": "Christian",
    "LastName": "Olmstead",
    "LastNameSuffix": "",
    "Position": "OL",
    "PositionLongName": "",
    "NAbbrev": "C. Olmstead",
    "Height": "6'4\"",
    "Weight": "302",
    "DOB": "",
    "POB": "",
    "Hometown": "",
    "Country": "",
    "CountryCode": "",
    "Nickname": "",
    "InjuryStatus": "",
    "InjuryDesc": "",
    "GfxId": 67,
    "Headshot": "",
    "Initials": "",
    "Scratch": true,
    "TrackingId": "",
    "TeamId": "5",
    "Affiliate": "",
    "CloudHeadshotURL": "https://res.cloudinary.com/xfl-production/image/upload/v1668132138/xfl-prod/headshots/Christian_Olmstead_21165.png",
    "SquadId": "",
    "College": "",
    "LeagueStatus": "",
    "PreviousTeamId": ""
  },
  {
    "OfficialId": "22443",
    "VisOrHome": "Visitor",
    "JerseyNum": "73",
    "FirstName": "Juwann",
    "LastName": "Bushell-Beatty",
    "LastNameSuffix": "",
    "Position": "OL",
    "PositionLongName": "",
    "NAbbrev": "J. Bushell-Beatty",
    "Height": "6'5\"",
    "Weight": "332",
    "DOB": "",
    "POB": "",
    "Hometown": "",
    "Country": "",
    "CountryCode": "",
    "Nickname": "",
    "InjuryStatus": "",
    "InjuryDesc": "",
    "GfxId": 73,
    "Headshot": "",
    "IsStarting": true,
    "Initials": "",
    "TrackingId": "",
    "TeamId": "5",
    "Affiliate": "",
    "CloudHeadshotURL": "",
    "SquadId": "",
    "College": "",
    "LeagueStatus": "",
    "Participated": true,
    "PreviousTeamId": ""
  },
  {
    "OfficialId": "20562",
    "VisOrHome": "Visitor",
    "JerseyNum": "74",
    "FirstName": "Steven",
    "LastName": "Gonzalez",
    "LastNameSuffix": "",
    "Position": "OL",
    "PositionLongName": "",
    "NAbbrev": "S. Gonzalez",
    "Height": "6'3\"",
    "Weight": "332",
    "DOB": "5/11/1997",
    "POB": "",
    "Age": 25,
    "Hometown": "",
    "Country": "",
    "CountryCode": "",
    "Nickname": "",
    "InjuryStatus": "",
    "InjuryDesc": "",
    "GfxId": 74,
    "Headshot": "",
    "IsStarting": true,
    "Initials": "",
    "TrackingId": "",
    "TeamId": "5",
    "Affiliate": "",
    "CloudHeadshotURL": "https://res.cloudinary.com/xfl-production/image/upload/v1668132138/xfl-prod/headshots/Steven_Gonzalez_20562.png",
    "SquadId": "",
    "College": "",
    "LeagueStatus": "",
    "Participated": true,
    "PreviousTeamId": ""
  },
  {
    "OfficialId": "20855",
    "VisOrHome": "Visitor",
    "JerseyNum": "75",
    "FirstName": "Jaryd",
    "LastName": "Jones-Smith",
    "LastNameSuffix": "",
    "Position": "OL",
    "PositionLongName": "",
    "NAbbrev": "J. Jones-Smith",
    "Height": "6'6\"",
    "Weight": "317",
    "DOB": "9/3/1995",
    "POB": "",
    "Age": 27,
    "Hometown": "",
    "Country": "",
    "CountryCode": "",
    "Nickname": "",
    "InjuryStatus": "",
    "InjuryDesc": "",
    "GfxId": 75,
    "Headshot": "",
    "IsStarting": true,
    "Initials": "",
    "TrackingId": "",
    "TeamId": "5",
    "Affiliate": "",
    "CloudHeadshotURL": "https://res.cloudinary.com/xfl-production/image/upload/v1668132138/xfl-prod/headshots/Jaryd_Jones-Smith_20855.png",
    "SquadId": "",
    "College": "",
    "LeagueStatus": "",
    "Participated": true,
    "PreviousTeamId": ""
  },
  {
    "OfficialId": "22869",
    "VisOrHome": "Visitor",
    "JerseyNum": "77",
    "FirstName": "Eric",
    "LastName": "Magwood",
    "LastNameSuffix": "",
    "Position": "OL",
    "PositionLongName": "",
    "NAbbrev": "E. Magwood",
    "Height": "6'4\"",
    "Weight": "300",
    "DOB": "",
    "POB": "",
    "Hometown": "",
    "Country": "",
    "CountryCode": "",
    "Nickname": "",
    "InjuryStatus": "",
    "InjuryDesc": "",
    "GfxId": 77,
    "Headshot": "",
    "Initials": "",
    "TrackingId": "",
    "TeamId": "5",
    "Affiliate": "",
    "CloudHeadshotURL": "",
    "SquadId": "",
    "College": "",
    "LeagueStatus": "",
    "PreviousTeamId": ""
  },
  {
    "OfficialId": "21843",
    "VisOrHome": "Visitor",
    "JerseyNum": "78",
    "FirstName": "Vadal",
    "LastName": "Alexander",
    "LastNameSuffix": "",
    "Position": "OL",
    "PositionLongName": "",
    "NAbbrev": "V. Alexander",
    "Height": "6'5\"",
    "Weight": "326",
    "DOB": "3/23/1994",
    "POB": "",
    "Age": 28,
    "Hometown": "",
    "Country": "",
    "CountryCode": "",
    "Nickname": "",
    "InjuryStatus": "",
    "InjuryDesc": "",
    "GfxId": 78,
    "Headshot": "",
    "IsStarting": true,
    "Initials": "",
    "TrackingId": "",
    "TeamId": "5",
    "Affiliate": "",
    "CloudHeadshotURL": "",
    "SquadId": "",
    "College": "",
    "LeagueStatus": "",
    "Participated": true,
    "PreviousTeamId": ""
  },
  {
    "OfficialId": "20397",
    "VisOrHome": "Visitor",
    "JerseyNum": "79",
    "FirstName": "Daishawn",
    "LastName": "Dixon",
    "LastNameSuffix": "",
    "Position": "OL",
    "PositionLongName": "",
    "NAbbrev": "D. Dixon",
    "Height": "6'4\"",
    "Weight": "325",
    "DOB": "6/19/1997",
    "POB": "",
    "Age": 25,
    "Hometown": "",
    "Country": "",
    "CountryCode": "",
    "Nickname": "",
    "InjuryStatus": "",
    "InjuryDesc": "",
    "GfxId": 79,
    "Headshot": "",
    "Initials": "",
    "Scratch": true,
    "TrackingId": "",
    "TeamId": "5",
    "Affiliate": "",
    "CloudHeadshotURL": "https://res.cloudinary.com/xfl-production/image/upload/v1668132138/xfl-prod/headshots/Daishawn_Dixon_20397.png",
    "SquadId": "",
    "College": "",
    "LeagueStatus": "",
    "PreviousTeamId": ""
  },
  {
    "OfficialId": "21546",
    "VisOrHome": "Visitor",
    "JerseyNum": "83",
    "FirstName": "Jordan",
    "LastName": "Thomas",
    "LastNameSuffix": "",
    "Position": "TE",
    "PositionLongName": "",
    "NAbbrev": "J. Thomas",
    "Height": "6'5\"",
    "Weight": "265",
    "DOB": "8/2/1996",
    "POB": "",
    "Age": 26,
    "Hometown": "",
    "Country": "",
    "CountryCode": "",
    "Nickname": "",
    "InjuryStatus": "",
    "InjuryDesc": "",
    "GfxId": 83,
    "Headshot": "",
    "Initials": "",
    "Scratch": true,
    "TrackingId": "",
    "TeamId": "5",
    "Affiliate": "",
    "CloudHeadshotURL": "https://res.cloudinary.com/xfl-production/image/upload/v1668132138/xfl-prod/headshots/Jordan_Thomas_21546.png",
    "SquadId": "",
    "College": "",
    "LeagueStatus": "",
    "PreviousTeamId": ""
  },
  {
    "OfficialId": "21501",
    "VisOrHome": "Visitor",
    "JerseyNum": "84",
    "FirstName": "Jake",
    "LastName": "Sutherland",
    "LastNameSuffix": "",
    "Position": "TE",
    "PositionLongName": "",
    "NAbbrev": "J. Sutherland",
    "Height": "6'4\"",
    "Weight": "241",
    "DOB": "",
    "POB": "",
    "Hometown": "",
    "Country": "",
    "CountryCode": "",
    "Nickname": "",
    "InjuryStatus": "",
    "InjuryDesc": "",
    "GfxId": 84,
    "Headshot": "",
    "IsStarting": true,
    "Initials": "",
    "TrackingId": "",
    "TeamId": "5",
    "Affiliate": "",
    "CloudHeadshotURL": "https://res.cloudinary.com/xfl-production/image/upload/v1668132138/xfl-prod/headshots/Jake_Sutherland_21501.png",
    "SquadId": "",
    "College": "",
    "LeagueStatus": "",
    "Participated": true,
    "PreviousTeamId": ""
  },
  {
    "OfficialId": "22333",
    "VisOrHome": "Visitor",
    "JerseyNum": "88",
    "FirstName": "Hakeem",
    "LastName": "Butler",
    "LastNameSuffix": "",
    "Position": "WR",
    "PositionLongName": "",
    "NAbbrev": "H. Butler",
    "Height": "6'5\"",
    "Weight": "227",
    "DOB": "5/16/1996",
    "POB": "",
    "Age": 26,
    "Hometown": "",
    "Country": "",
    "CountryCode": "",
    "Nickname": "",
    "InjuryStatus": "",
    "InjuryDesc": "",
    "GfxId": 88,
    "Headshot": "",
    "Initials": "",
    "TrackingId": "",
    "TeamId": "5",
    "Affiliate": "",
    "CloudHeadshotURL": "",
    "SquadId": "",
    "College": "",
    "LeagueStatus": "",
    "Participated": true,
    "PreviousTeamId": ""
  },
  {
    "OfficialId": "20061",
    "VisOrHome": "Visitor",
    "JerseyNum": "90",
    "FirstName": "Kevin",
    "LastName": "Atkins",
    "LastNameSuffix": "",
    "Position": "DL",
    "PositionLongName": "",
    "NAbbrev": "K. Atkins",
    "Height": "6'2\"",
    "Weight": "314",
    "DOB": "",
    "POB": "",
    "Hometown": "",
    "Country": "",
    "CountryCode": "",
    "Nickname": "",
    "InjuryStatus": "",
    "InjuryDesc": "",
    "GfxId": 90,
    "Headshot": "",
    "IsStarting": true,
    "Initials": "",
    "TrackingId": "",
    "TeamId": "5",
    "Affiliate": "",
    "CloudHeadshotURL": "",
    "SquadId": "",
    "College": "",
    "LeagueStatus": "",
    "Participated": true,
    "PreviousTeamId": ""
  },
  {
    "OfficialId": "21578",
    "VisOrHome": "Visitor",
    "JerseyNum": "91",
    "FirstName": "Taniela",
    "LastName": "Tupou",
    "LastNameSuffix": "",
    "Position": "DL",
    "PositionLongName": "",
    "NAbbrev": "T. Tupou",
    "Height": "6'1\"",
    "Weight": "284",
    "DOB": "12/13/1992",
    "POB": "",
    "Age": 30,
    "Hometown": "",
    "Country": "",
    "CountryCode": "",
    "Nickname": "",
    "InjuryStatus": "",
    "InjuryDesc": "",
    "GfxId": 91,
    "Headshot": "",
    "Initials": "",
    "TrackingId": "",
    "TeamId": "5",
    "Affiliate": "",
    "CloudHeadshotURL": "https://res.cloudinary.com/xfl-production/image/upload/v1668132138/xfl-prod/headshots/Taniela_Tupou_21578.png",
    "SquadId": "",
    "College": "",
    "LeagueStatus": "",
    "Participated": true,
    "PreviousTeamId": ""
  },
  {
    "OfficialId": "21927",
    "VisOrHome": "Visitor",
    "JerseyNum": "93",
    "FirstName": "Damion",
    "LastName": "Daniels",
    "LastNameSuffix": "",
    "Position": "DL",
    "PositionLongName": "",
    "NAbbrev": "D. Daniels",
    "Height": "6'1\"",
    "Weight": "302",
    "DOB": "8/31/1999",
    "POB": "",
    "Age": 23,
    "Hometown": "",
    "Country": "",
    "CountryCode": "",
    "Nickname": "",
    "InjuryStatus": "",
    "InjuryDesc": "",
    "GfxId": 93,
    "Headshot": "",
    "Initials": "",
    "TrackingId": "",
    "TeamId": "5",
    "Affiliate": "",
    "CloudHeadshotURL": "https://res.cloudinary.com/xfl-production/image/upload/v1668132138/xfl-prod/headshots/Damion_Daniels_21927.png",
    "SquadId": "",
    "College": "",
    "LeagueStatus": "",
    "Participated": true,
    "PreviousTeamId": ""
  },
  {
    "OfficialId": "20971",
    "VisOrHome": "Visitor",
    "JerseyNum": "95",
    "FirstName": "Elorm",
    "LastName": "Lumor",
    "LastNameSuffix": "",
    "Position": "DL",
    "PositionLongName": "",
    "NAbbrev": "E. Lumor",
    "Height": "6'3\"",
    "Weight": "242",
    "DOB": "",
    "POB": "",
    "Hometown": "",
    "Country": "",
    "CountryCode": "",
    "Nickname": "",
    "InjuryStatus": "",
    "InjuryDesc": "",
    "GfxId": 95,
    "Headshot": "",
    "IsStarting": true,
    "Initials": "",
    "TrackingId": "",
    "TeamId": "5",
    "Affiliate": "",
    "CloudHeadshotURL": "https://res.cloudinary.com/xfl-production/image/upload/v1668132138/xfl-prod/headshots/Elorm_Lumor_20971.png",
    "SquadId": "",
    "College": "",
    "LeagueStatus": "",
    "Participated": true,
    "PreviousTeamId": ""
  },
  {
    "OfficialId": "20965",
    "VisOrHome": "Visitor",
    "JerseyNum": "96",
    "FirstName": "LaCale",
    "LastName": "London",
    "LastNameSuffix": "",
    "Position": "DL",
    "PositionLongName": "",
    "NAbbrev": "L. London",
    "Height": "6'3\"",
    "Weight": "297",
    "DOB": "8/5/1997",
    "POB": "",
    "Age": 25,
    "Hometown": "",
    "Country": "",
    "CountryCode": "",
    "Nickname": "",
    "InjuryStatus": "",
    "InjuryDesc": "",
    "GfxId": 96,
    "Headshot": "",
    "IsStarting": true,
    "Initials": "",
    "TrackingId": "",
    "TeamId": "5",
    "Affiliate": "",
    "CloudHeadshotURL": "",
    "SquadId": "",
    "College": "",
    "LeagueStatus": "",
    "Participated": true,
    "PreviousTeamId": ""
  },
  {
    "OfficialId": "22386",
    "VisOrHome": "Visitor",
    "JerseyNum": "98",
    "FirstName": "Freedom",
    "LastName": "Akinmoladun",
    "LastNameSuffix": "",
    "Position": "DL",
    "PositionLongName": "",
    "NAbbrev": "F. Akinmoladun",
    "Height": "6'3\"",
    "Weight": "301",
    "DOB": "",
    "POB": "",
    "Hometown": "",
    "Country": "",
    "CountryCode": "",
    "Nickname": "",
    "InjuryStatus": "",
    "InjuryDesc": "",
    "GfxId": 98,
    "Headshot": "",
    "Initials": "",
    "TrackingId": "",
    "TeamId": "5",
    "Affiliate": "",
    "CloudHeadshotURL": "",
    "SquadId": "",
    "College": "",
    "LeagueStatus": "",
    "Participated": true,
    "PreviousTeamId": ""
  },
  {
    "OfficialId": "21319",
    "VisOrHome": "Visitor",
    "JerseyNum": "99",
    "FirstName": "Gelen",
    "LastName": "Robinson",
    "LastNameSuffix": "",
    "Position": "DL",
    "PositionLongName": "",
    "NAbbrev": "G. Robinson",
    "Height": "6'1\"",
    "Weight": "275",
    "DOB": "",
    "POB": "",
    "Hometown": "",
    "Country": "",
    "CountryCode": "",
    "Nickname": "",
    "InjuryStatus": "",
    "InjuryDesc": "",
    "GfxId": 99,
    "Headshot": "",
    "Initials": "",
    "TrackingId": "",
    "TeamId": "5",
    "Affiliate": "",
    "CloudHeadshotURL": "https://res.cloudinary.com/xfl-production/image/upload/v1668132138/xfl-prod/headshots/Gelen_Robinson_21319.png",
    "SquadId": "",
    "College": "",
    "LeagueStatus": "",
    "Participated": true,
    "PreviousTeamId": ""
  }
]